pilotes
test
