Metadata-Version: 1.1
Name: pilote
Version: 0.0.9
Summary: UNKNOWN
Home-page: https://github.com/omprakash1989/pilote/
Author: Om Prakash
Author-email: omprakash@gofynd.com
License: MIT License
Keywords: Integrate Delivery Partners like bluedart,delhivery,ecomm,fedex etc.
Platform: any
Classifier: Development Status :: 2 - Pre-Alpha
Classifier: Intended Audience :: Developers
Classifier: License :: OSI Approved :: MIT License
Classifier: License :: OSI Approved :: Academic Free License (AFL)
Classifier: Programming Language :: Python
Classifier: Programming Language :: Python :: 2
Classifier: Programming Language :: Python :: 2.5
Classifier: Programming Language :: Python :: 2.6
Classifier: Programming Language :: Python :: 2.7
Classifier: Programming Language :: Python :: Implementation :: CPython
Classifier: Programming Language :: Python :: Implementation :: PyPy
Classifier: Topic :: Software Development :: Libraries :: Python Modules
